Pokemon_Library_ENattRL/__init__.py
Pokemon_Library_ENattRL/pokemon.csv
Pokemon_Library_ENattRL/random_pokemon.py
Pokemon_Library_ENattRL-1.0.0.dist-info/METADATA
Pokemon_Library_ENattRL-1.0.0.dist-info/WHEEL
Pokemon_Library_ENattRL-1.0.0.dist-info/top_level.txt
Pokemon_Library_ENattRL-1.0.0.dist-info/RECORD
