Metadata-Version: 2.1
Name: Pokemon-Library-ENattRL
Version: 1.0.0
Summary: Libreria para buscar un pokemon aleatorio
Author: Natt
Author-email: 202224050_ramos@tesch.edu.mx
Requires-Dist: pandas
